csobpg/__init__.py
csobpg/v19/__init__.py
csobpg/v19/api.py
csobpg/v19/errors.py
csobpg/v19/key.py
csobpg/v19/models/__init__.py
csobpg/v19/models/actions.py
csobpg/v19/models/cart.py
csobpg/v19/models/currency.py
csobpg/v19/models/customer/__init__.py
csobpg/v19/models/customer/account.py
csobpg/v19/models/customer/data.py
csobpg/v19/models/customer/login.py
csobpg/v19/models/fields.py
csobpg/v19/models/fingerprint.py
csobpg/v19/models/order/__init__.py
csobpg/v19/models/order/address.py
csobpg/v19/models/order/data.py
csobpg/v19/models/order/delivery.py
csobpg/v19/models/payment.py
csobpg/v19/models/webpage.py
csobpg/v19/request/__init__.py
csobpg/v19/request/applepay_echo.py
csobpg/v19/request/applepay_init.py
csobpg/v19/request/applepay_process.py
csobpg/v19/request/base.py
csobpg/v19/request/dttm.py
csobpg/v19/request/echo.py
csobpg/v19/request/googlepay_echo.py
csobpg/v19/request/googlepay_init.py
csobpg/v19/request/googlepay_process.py
csobpg/v19/request/merchant.py
csobpg/v19/request/oneclick_echo.py
csobpg/v19/request/oneclick_init.py
csobpg/v19/request/oneclick_process.py
csobpg/v19/request/payment_close.py
csobpg/v19/request/payment_init.py
csobpg/v19/request/payment_process.py
csobpg/v19/request/payment_refund.py
csobpg/v19/request/payment_reverse.py
csobpg/v19/request/payment_status.py
csobpg/v19/request/url.py
csobpg/v19/response/__init__.py
csobpg/v19/response/applepay_echo.py
csobpg/v19/response/applepay_payment_init.py
csobpg/v19/response/applepay_payment_process.py
csobpg/v19/response/base.py
csobpg/v19/response/googlepay_echo.py
csobpg/v19/response/googlepay_payment_init.py
csobpg/v19/response/googlepay_payment_process.py
csobpg/v19/response/oneclick_echo.py
csobpg/v19/response/oneclick_payment_init.py
csobpg/v19/response/oneclick_payment_process.py
csobpg/v19/response/payment_close.py
csobpg/v19/response/payment_init.py
csobpg/v19/response/payment_process.py
csobpg/v19/response/payment_refund.py
csobpg/v19/response/payment_reverse.py
csobpg-0.5.2.dist-info/LICENSE
csobpg-0.5.2.dist-info/METADATA
csobpg-0.5.2.dist-info/WHEEL
csobpg-0.5.2.dist-info/RECORD
