Metadata-Version: 2.3
Name: csobpg
Version: 0.5.2
Summary: Library for communication with ČSOB API
License: MIT
Author: Andrii Nechaiev
Author-email: andrewnech@gmail.com
Requires-Python: >=3.9,<3.13
Classifier: Development Status :: 4 - Beta
Classifier: Intended Audience :: Developers
Classifier: License :: OSI Approved :: MIT License
Classifier: Operating System :: POSIX :: Linux
Classifier: Programming Language :: Python
Classifier: Programming Language :: Python :: 3
Classifier: Programming Language :: Python :: 3.9
Classifier: Programming Language :: Python :: 3.10
Classifier: Programming Language :: Python :: 3.11
Classifier: Programming Language :: Python :: 3.12
Classifier: Programming Language :: Python :: 3 :: Only
Classifier: Programming Language :: Python :: Implementation :: CPython
Classifier: Topic :: Software Development :: Libraries
Classifier: Topic :: Utilities
Requires-Dist: httprest (>=0.3,<0.4)
Requires-Dist: pycryptodome (>=3.17,<4.0)
Project-URL: Repository, https://github.com/litteratum/csobpg
